pybrownomics/__init__.py
pybrownomics/base/__init__.py
pybrownomics/base/schema.py
pybrownomics/base/simulation.py
pybrownomics/brown/simulation.py
pybrownomics/brown/src/generator.py
pybrownomics/brown/src/simulator.py
pybrownomics/control/README.md
pybrownomics/control/simulation.py
pybrownomics/control/src/__init__.py
pybrownomics/control/src/game.py
pybrownomics/control/src/solver.py
pybrownomics/control/src/token_dynamics.py
pybrownomics/control/src/token_economy.py
pybrownomics/tests/test_brown_model.py
pybrownomics/tests/test_control_model.py
pybrownomics-0.2.3.dist-info/LICENSE
pybrownomics-0.2.3.dist-info/METADATA
pybrownomics-0.2.3.dist-info/WHEEL
pybrownomics-0.2.3.dist-info/RECORD
