Metadata-Version: 2.1
Name: pybrownomics
Version: 0.2.3
Summary: 
License: MIT
Author: Lorenzo Alencar Tomaz
Author-email: lolo.tomaz@gmail.com
Requires-Python: >=3.8.0,<3.12
Classifier: License :: OSI Approved :: MIT License
Classifier: Programming Language :: Python :: 3
Classifier: Programming Language :: Python :: 3.8
Classifier: Programming Language :: Python :: 3.9
Classifier: Programming Language :: Python :: 3.10
Classifier: Programming Language :: Python :: 3.11
Requires-Dist: matplotlib (>=3.7.2,<4.0.0)
Requires-Dist: numpy (>=1.24.2,<2.0.0)
Requires-Dist: pandas (>=2.0.3,<3.0.0)
Requires-Dist: scipy (>=1.10.1,<2.0.0)
